{
    "DeepCpG_DNA": {
        "url": "https://zenodo.org/record/5644007/files/kipoi-docker_sharedpy3keras2.sif?download=1",
        "name": "kipoi-docker_sharedpy3keras2"
    },
    "CpGenie": {
        "url": "https://zenodo.org/record/5644005/files/kipoi-docker_sharedpy3keras1.2.sif?download=1",
        "name": "kipoi-docker_sharedpy3keras1.2"
    },
    "Divergent421": {
        "url": "https://zenodo.org/record/5644005/files/kipoi-docker_sharedpy3keras1.2.sif?download=1",
        "name": "kipoi-docker_sharedpy3keras1.2"
    },
    "Basenji": {
        "url": "https://zenodo.org/record/5644007/files/kipoi-docker_sharedpy3keras2.sif?download=1",
        "name": "kipoi-docker_sharedpy3keras2"
    },
    "Basset": {
        "url": "https://zenodo.org/record/5644007/files/kipoi-docker_sharedpy3keras2.sif?download=1",
        "name": "kipoi-docker_sharedpy3keras2"
    },
    "HAL": {
        "url": "https://zenodo.org/record/5644007/files/kipoi-docker_sharedpy3keras2.sif?download=1",
        "name": "kipoi-docker_sharedpy3keras2"
    },
    "DeepSEA": {
        "url": "https://zenodo.org/record/5644007/files/kipoi-docker_sharedpy3keras2.sif?download=1",
        "name": "kipoi-docker_sharedpy3keras2"
    },
    "Optimus_5Prime": {
        "url": "https://zenodo.org/record/5644007/files/kipoi-docker_sharedpy3keras2.sif?download=1",
        "name": "kipoi-docker_sharedpy3keras2"
    },
    "labranchor": {
        "url": "https://zenodo.org/record/5644007/files/kipoi-docker_sharedpy3keras2.sif?download=1",
        "name": "kipoi-docker_sharedpy3keras2"
    },
    "CleTimer": {
        "url": "https://zenodo.org/record/5644007/files/kipoi-docker_sharedpy3keras2.sif?download=1",
        "name": "kipoi-docker_sharedpy3keras2"
    },
    "SiSp": {
        "url": "https://zenodo.org/record/5644007/files/kipoi-docker_sharedpy3keras2.sif?download=1",
        "name": "kipoi-docker_sharedpy3keras2"
    },
    "FactorNet": {
        "url": "https://zenodo.org/record/5644007/files/kipoi-docker_sharedpy3keras2.sif?download=1",
        "name": "kipoi-docker_sharedpy3keras2"
    },
    "pwm_HOCOMOCO": {
        "url": "https://zenodo.org/record/5644007/files/kipoi-docker_sharedpy3keras2.sif?download=1",
        "name": "kipoi-docker_sharedpy3keras2"
    },
    "MaxEntScan": {
        "url": "https://zenodo.org/record/5644007/files/kipoi-docker_sharedpy3keras2.sif?download=1",
        "name": "kipoi-docker_sharedpy3keras2"
    },
    "DeepBind": {
        "url": "https://zenodo.org/record/5644007/files/kipoi-docker_sharedpy3keras2.sif?download=1",
        "name": "kipoi-docker_sharedpy3keras2"
    },
    "lsgkm-SVM": {
        "url": "https://zenodo.org/record/5644007/files/kipoi-docker_sharedpy3keras2.sif?download=1",
        "name": "kipoi-docker_sharedpy3keras2"
    },
    "rbp_eclip": {
        "url": "https://zenodo.org/record/5644007/files/kipoi-docker_sharedpy3keras2.sif?download=1",
        "name": "kipoi-docker_sharedpy3keras2"
    },
    "MPRA-DragoNN": {
        "url": "https://zenodo.org/record/5643980/files/kipoi-docker_mpra-dragonn.sif?download=1",
        "name": "kipoi-docker_mpra-dragonn"
    },
    "extended_coda": {
        "url": "https://zenodo.org/record/5643936/files/kipoi-docker_extended_coda.sif?download=1",
        "name": "kipoi-docker_extended_coda"
    },
    "MMSplice/pathogenicity": {
        "url": "https://zenodo.org/record/5643976/files/kipoi-docker_mmsplice.sif?download=1",
        "name": "kipoi-docker_mmsplice"
    },
    "MMSplice/splicingEfficiency": {
        "url": "https://zenodo.org/record/5643976/files/kipoi-docker_mmsplice.sif?download=1",
        "name": "kipoi-docker_mmsplice"
    },
    "MMSplice/deltaLogitPSI": {
        "url": "https://zenodo.org/record/5643976/files/kipoi-docker_mmsplice.sif?download=1",
        "name": "kipoi-docker_mmsplice"
    },
    "MMSplice/modularPredictions": {
        "url": "https://zenodo.org/record/5643976/files/kipoi-docker_mmsplice.sif?download=1",
        "name": "kipoi-docker_mmsplice"
    },
    "MMSplice/mtsplice": {
        "url": "https://zenodo.org/record/5643967/files/kipoi-docker_mmsplice-mtsplice.sif?download=1",
        "name": "kipoi-docker_mmsplice-mtsplice"
    },
    "DeepMEL": {
        "url": "https://zenodo.org/record/5643863/files/kipoi-docker_deepmel.sif?download=1",
        "name": "kipoi-docker_deepmel"
    },
    "Framepool": {
        "url": "https://zenodo.org/record/5643942/files/kipoi-docker_framepool.sif?download=1",
        "name": "kipoi-docker_framepool"
    },
    "KipoiSplice": {
        "url": "https://zenodo.org/record/5643955/files/kipoi-docker_kipoisplice.sif?download=1",
        "name": "kipoi-docker_kipoisplice"
    },
    "deepTarget": {
        "url": "https://zenodo.org/record/5643929/files/kipoi-docker_deeptarget.sif?download=1",
        "name": "kipoi-docker_deeptarget"
    },
    "AttentiveChrome": {
        "url": "https://zenodo.org/record/5638781/files/kipoi-docker_attentivechrome.sif?download=1",
        "name": "kipoi-docker_attentivechrome"
    },
    "BPNet-OSKN": {
        "url": "https://zenodo.org/record/5643831/files/kipoi-docker_bpnet-oskn.sif?download=1",
        "name": "kipoi-docker_bpnet-oskn"
    },
    "SeqVec": {
        "url": "https://zenodo.org/record/5643982/files/kipoi-docker_seqvec.sif?download=1",
        "name": "kipoi-docker_seqvec"
    },
    "Xpresso": {
        "url": "https://zenodo.org/record/5644007/files/kipoi-docker_sharedpy3keras2.sif?download=1",
        "name": "kipoi-docker_sharedpy3keras2"
    },
    "epidermal_basset": {
        "url": "https://zenodo.org/api/files/909c448f-0740-44bb-959a-21e643e0440a/kipoi-docker_sharedpy3keras1.2.sif",
        "name": "kipoi-docker_sharedpy3keras1.2"
    },
    "DeepFlyBrain": {
        "url": "https://zenodo.org/record/5643854/files/kipoi-docker_deepflybrain.sif?download=1",
        "name": "kipoi-docker_deepflybrain"
    },
    "APARENT/site_probabilities": {
        "url": "https://zenodo.org/record/5643783/files/kipoi-docker_aparent-site_probabilities.sif?download=1",
        "name": "kipoi-docker_aparent-site_probabilities"
    },
    "APARENT/veff": {
        "url": "https://zenodo.org/record/5643822/files/kipoi-docker_aparent-veff.sif?download=1",
        "name": "kipoi-docker_aparent-veff"
    }
}